{
    "time_data": {
        "10": [
            "NA"
        ],
        "20": [
            "NA"
        ],
        "50": [
            "NA"
        ],
        "100": [
            "NA"
        ],
        "200": [
            "NA"
        ],
        "500": [
            "NA"
        ],
        "1000": [
            "NA"
        ],
        "2000": [
            "NA"
        ],
        "5000": [
            "NA"
        ],
        "10000": [
            "NA"
        ]
    },
    "max_rows": 10000,
    "max_time": 6034.982312202454
}